devops_spt/__init__.py
devops_spt/directory.py
devops_spt/external_dependency.py
devops_spt/external_version.py
devops_spt/gradle_dependency.py
devops_spt/gradle_version.py
devops_spt/kotlin_dependency.py
devops_spt/kotlin_version.py
devops_spt-0.5.0.dist-info/LICENSE
devops_spt-0.5.0.dist-info/METADATA
devops_spt-0.5.0.dist-info/WHEEL
devops_spt-0.5.0.dist-info/top_level.txt
devops_spt-0.5.0.dist-info/RECORD
