Metadata-Version: 2.1
Name: devops-spt
Version: 0.5.0
Summary: Devops support functions in a Python package
Home-page: https://github.com/dksmiffs/devops-spt
Author: Dave Smith
Author-email: dave.k.smith@gmail.com
License: MIT
Keywords: devops
Platform: UNKNOWN
Classifier: Development Status :: 2 - Pre-Alpha
Classifier: Intended Audience :: Developers
Classifier: Topic :: Software Development :: Build Tools
Classifier: License :: OSI Approved :: MIT License
Classifier: Natural Language :: English
Classifier: Programming Language :: Python :: 3.7
